gisterize/__init__.py
gisterize/gisterize.py
gisterize/setup.py
gisterize-1.1.5.dist-info/METADATA
gisterize-1.1.5.dist-info/RECORD
gisterize-1.1.5.dist-info/WHEEL
gisterize-1.1.5.dist-info/top_level.txt
