Metadata-Version: 2.1
Name: gisterize
Version: 1.1.5
Summary: Gist utility to download data
Home-page: https://github.com/schemadesign/gisterize
Author: Quinton Teas
Author-email: quinton@schemadesign.com
License: UNKNOWN
Keywords: gist data visualization wrapper endpoint
Platform: UNKNOWN
